odoo/addons/web_view_leaflet_map_partner/README.rst
odoo/addons/web_view_leaflet_map_partner/__init__.py
odoo/addons/web_view_leaflet_map_partner/__manifest__.py
odoo/addons/web_view_leaflet_map_partner/demo/res_partner.xml
odoo/addons/web_view_leaflet_map_partner/i18n/it.po
odoo/addons/web_view_leaflet_map_partner/i18n/web_view_leaflet_map_partner.pot
odoo/addons/web_view_leaflet_map_partner/models/__init__.py
odoo/addons/web_view_leaflet_map_partner/models/res_partner.py
odoo/addons/web_view_leaflet_map_partner/readme/CONFIGURE.rst
odoo/addons/web_view_leaflet_map_partner/readme/CONTRIBUTORS.rst
odoo/addons/web_view_leaflet_map_partner/readme/DESCRIPTION.rst
odoo/addons/web_view_leaflet_map_partner/readme/USAGE.rst
odoo/addons/web_view_leaflet_map_partner/static/description/icon.png
odoo/addons/web_view_leaflet_map_partner/static/description/index.html
odoo/addons/web_view_leaflet_map_partner/static/description/res_partner_button.png
odoo/addons/web_view_leaflet_map_partner/static/description/res_partner_map.png
odoo/addons/web_view_leaflet_map_partner/views/res_partner.xml
odoo_addon_web_view_leaflet_map_partner-16.0.1.0.0.5.dist-info/METADATA
odoo_addon_web_view_leaflet_map_partner-16.0.1.0.0.5.dist-info/WHEEL
odoo_addon_web_view_leaflet_map_partner-16.0.1.0.0.5.dist-info/top_level.txt
odoo_addon_web_view_leaflet_map_partner-16.0.1.0.0.5.dist-info/RECORD
